raster_tester/__init__.py
raster_tester/aligned.py
raster_tester/compare.py
raster_tester/crosses_dateline.py
raster_tester/empty.py
raster_tester/utils.py
raster_tester/scripts/__init__.py
raster_tester/scripts/cli.py
raster_tester-0.10.0.dist-info/DESCRIPTION.rst
raster_tester-0.10.0.dist-info/METADATA
raster_tester-0.10.0.dist-info/RECORD
raster_tester-0.10.0.dist-info/WHEEL
raster_tester-0.10.0.dist-info/entry_points.txt
raster_tester-0.10.0.dist-info/metadata.json
raster_tester-0.10.0.dist-info/pbr.json
raster_tester-0.10.0.dist-info/top_level.txt
