Metadata-Version: 2.0
Name: raster-tester
Version: 0.10.0
Summary: Tools for testing rasters
Home-page: https://github.com/mapbox/raster-tester
Author: Camilla Mahon
Author-email: camilla@mapbox.com
License: MIT
Platform: UNKNOWN
Requires-Dist: click
Requires-Dist: rasterio
Provides-Extra: test
Requires-Dist: pytest; extra == 'test'
Requires-Dist: pytest-cov; extra == 'test'
Requires-Dist: codecov; extra == 'test'
